LICENSE
MANIFEST.in
README.md
requirements.txt
setup.py
jamdict/__init__.py
jamdict/__main__.py
jamdict/__version__.py
jamdict/config.py
jamdict/jmdict.py
jamdict/jmdict_sqlite.py
jamdict/jmnedict_sqlite.py
jamdict/kanjidic2.py
jamdict/kanjidic2_sqlite.py
jamdict/krad.py
jamdict/tools.py
jamdict/util.py
jamdict.egg-info/PKG-INFO
jamdict.egg-info/SOURCES.txt
jamdict.egg-info/dependency_links.txt
jamdict.egg-info/requires.txt
jamdict.egg-info/top_level.txt
jamdict/data/config_template.json
jamdict/data/kradfile-u.gz
jamdict/data/radkfile.gz
jamdict/data/setup_jmdict.sql
jamdict/data/setup_jmnedict.sql
jamdict/data/setup_kanjidic2.sql
test/test_jamdict.py
test/test_jmdict_sqlite.py
test/test_jmnedict.py
test/test_kanjidic2_sqlite.py
test/test_krad.py