Metadata-Version: 2.1
Name: jamdict
Version: 0.1a11
Summary: Python library for using Japanese dictionaries and resources (Jim Breen's JMdict, KanjiDic2, KRADFILE, JMnedict)
Home-page: https://github.com/neocl/jamdict
Author: Le Tuan Anh
Author-email: tuananh.ke@gmail.com
License: MIT License
Project-URL: Bug Tracker, https://github.com/neocl/jamdict/issues
Project-URL: Source Code, https://github.com/neocl/jamdict/
Keywords: dictionary,japanese,kanji,japanese-language,jmdict,japanese-study,kanjidic2,japanese-dictionary,jamdict
Platform: any
Classifier: Programming Language :: Python :: 3
Classifier: Programming Language :: Python :: 3.6
Classifier: Programming Language :: Python :: 3.7
Classifier: Programming Language :: Python :: 3.8
Classifier: Programming Language :: Python :: 3.9
Classifier: Development Status :: 3 - Alpha
Classifier: Natural Language :: Japanese
Classifier: Natural Language :: English
Classifier: Environment :: Plugins
Classifier: Intended Audience :: Developers
Classifier: License :: OSI Approved :: MIT License
Classifier: Operating System :: OS Independent
Classifier: Topic :: Database
Classifier: Topic :: Text Processing :: Linguistic
Classifier: Topic :: Software Development :: Libraries :: Python Modules
Requires-Python: >=3.6
